[
  {
    "ParameterKey": "DynamoDBModelTableReadIOPS",
    "ParameterValue": "5"
  },
  {
    "ParameterKey": "DynamoDBEnableServerSideEncryption",
    "ParameterValue": "false"
  },
  {
    "ParameterKey": "DynamoDBEnablePointInTimeRecovery",
    "ParameterValue": "false"
  },
  {
    "ParameterKey": "DynamoDBBillingMode",
    "ParameterValue": "PAY_PER_REQUEST"
  },
  {
    "ParameterKey": "S3DeploymentBucket",
    "ParameterValue": "amplify-discussions-main-d5a80-deployment"
  },
  {
    "ParameterKey": "DynamoDBModelTableWriteIOPS",
    "ParameterValue": "5"
  },
  {
    "ParameterKey": "env",
    "ParameterValue": "main"
  },
  {
    "ParameterKey": "S3DeploymentRootKey",
    "ParameterValue": "amplify-appsync-files/db92bad357b2590353e82db2f2ec7d0fc9cfd30d"
  },
  {
    "ParameterKey": "AppSyncApiName",
    "ParameterValue": "discussions"
  }
]